helloyoshi/__init__.py
helloyoshi/hello.py
helloyoshi-0.0.3.dist-info/METADATA
helloyoshi-0.0.3.dist-info/WHEEL
helloyoshi-0.0.3.dist-info/top_level.txt
helloyoshi-0.0.3.dist-info/RECORD
