Metadata-Version: 2.1
Name: helloyoshi
Version: 0.0.3
Summary: Basic Hello Package
Home-page: UNKNOWN
Author: Yoshi Bansal
Author-email: <bansalyoshi@gmail.com>
License: UNKNOWN
Keywords: python,hello,yoshi,bansal
Platform: UNKNOWN
Classifier: Development Status :: 1 - Planning
Classifier: Intended Audience :: Developers
Classifier: Programming Language :: Python :: 3
Classifier: Operating System :: Unix
Classifier: Operating System :: MacOS :: MacOS X
Classifier: Operating System :: Microsoft :: Windows
Requires-Dist: numpy
Requires-Dist: pandas
Requires-Dist: pyfiglet
